pytask_julia/__init__.py
pytask_julia/_version.py
pytask_julia/collect.py
pytask_julia/config.py
pytask_julia/execute.py
pytask_julia/plugin.py
pytask_julia/py.typed
pytask_julia/serialization.py
pytask_julia/shared.py
pytask_julia-0.4.0.dist-info/LICENSE
pytask_julia-0.4.0.dist-info/METADATA
pytask_julia-0.4.0.dist-info/WHEEL
pytask_julia-0.4.0.dist-info/entry_points.txt
pytask_julia-0.4.0.dist-info/top_level.txt
pytask_julia-0.4.0.dist-info/RECORD
