Metadata-Version: 2.1
Name: pytask-julia
Version: 0.4.0
Summary: A Pytask plugin for Julia
Home-page: https://github.com/pytask-dev/pytask-julia
Author: Tobias Raabe
Author-email: raabe@posteo.de
License: MIT
Project-URL: Changelog, https://github.com/pytask-dev/pytask-julia/blob/main/CHANGES.md
Project-URL: Documentation, https://github.com/pytask-dev/pytask-julia
Project-URL: Github, https://github.com/pytask-dev/pytask-julia
Project-URL: Tracker, https://github.com/pytask-dev/pytask-julia/issues
Platform: any
Classifier: Development Status :: 4 - Beta
Classifier: License :: OSI Approved :: MIT License
Classifier: Operating System :: OS Independent
Classifier: Programming Language :: Python :: 3
Classifier: Programming Language :: Python :: 3 :: Only
Requires-Python: >=3.8
License-File: LICENSE
Requires-Dist: pluggy >=1.0.0
Requires-Dist: pytask >=0.4.0
